chaeritas/__init__.py
chaeritas/stride/__init__.py
chaeritas-0.0.1.dist-info/licenses/LICENSE
chaeritas-0.0.1.dist-info/METADATA
chaeritas-0.0.1.dist-info/WHEEL
chaeritas-0.0.1.dist-info/top_level.txt
chaeritas-0.0.1.dist-info/RECORD
