Metadata-Version: 2.4
Name: chaeritas
Version: 0.0.1
Summary: Skeleton package for chaeritas
Author-email: Chaeyun Ko <chaeyuniris@gmail.com>
License: AGPL-3.0
Project-URL: Homepage, https://github.com/chaeritas/chaeritas
Requires-Python: >=3.8
License-File: LICENSE
Dynamic: license-file
